import7z.cp37-win_amd64.pyd
import7z-0.1.0.dist-info/LICENSE
import7z-0.1.0.dist-info/METADATA
import7z-0.1.0.dist-info/WHEEL
import7z-0.1.0.dist-info/top_level.txt
import7z-0.1.0.dist-info/RECORD
