Metadata-Version: 2.1
Name: import7z
Version: 0.1.0
Summary: Import Python modules from 7z archives.
Home-page: https://github.com/leejeonghun/import7z
Author: Jeonghun Lee
License: UNKNOWN
Platform: any
Classifier: License :: OSI Approved :: Python Software Foundation License
Classifier: Operating System :: MacOS :: MacOS X
Classifier: Operating System :: Microsoft :: Windows
Classifier: Operating System :: POSIX
Classifier: Programming Language :: Python
